README.md
setup.cfg
setup.py
dsutp_custom_logger/__init__.py
dsutp_custom_logger/json_formatter.py
dsutp_custom_logger/logger.py
dsutp_custom_logger/stream.py
dsutp_custom_logger/tracer.py
dsutp_custom_logger.egg-info/PKG-INFO
dsutp_custom_logger.egg-info/SOURCES.txt
dsutp_custom_logger.egg-info/dependency_links.txt
dsutp_custom_logger.egg-info/requires.txt
dsutp_custom_logger.egg-info/top_level.txt