Metadata-Version: 2.1
Name: dsutp-custom-logger
Version: 1.0.1
Summary: Python module custom logging
Home-page: https://github.com/Nurik121/dsutp_custom_logger
Download-URL: https://github.com/Nurik121/dsutp_custom_logger/archive/main.zip
Author: Nurtaza
Author-email: nurik.kulikov@mail.ru
License: Apache License, Version 2.0, see LICENSE file
